neuro_bump_version/__init__.py
neuro_bump_version/main.py
neuro_bump_version-21.12.5.dist-info/entry_points.txt
neuro_bump_version-21.12.5.dist-info/LICENSE
neuro_bump_version-21.12.5.dist-info/WHEEL
neuro_bump_version-21.12.5.dist-info/METADATA
neuro_bump_version-21.12.5.dist-info/RECORD
