Metadata-Version: 2.1
Name: neuro-bump-version
Version: 21.12.5
Summary: Bump version for Neu.ro projects
Home-page: https://github.com/neuro-inc/neuro-bump-version
License: Apache-2.0
Author: Andrew Svetlov
Author-email: andrew.svetlov@gmail.com
Requires-Python: >=3.7
Classifier: License :: OSI Approved :: Apache Software License
Classifier: Programming Language :: Python :: 3
Classifier: Programming Language :: Python :: 3.10
Classifier: Programming Language :: Python :: 3.7
Classifier: Programming Language :: Python :: 3.8
Classifier: Programming Language :: Python :: 3.9
Classifier: Topic :: Software Development :: Build Tools
Requires-Dist: click (>=8.0.1,<8.1.0)
Requires-Dist: packaging (>=21.3,<22.0)
Project-URL: Repository, https://github.com/neuro-inc/neuro-bump-version
